spacy/_ml.py
spacy/symbols.cpython-36m-x86_64-linux-gnu.so
spacy/typedefs.pxd
spacy/lexeme.pyx
spacy/vocab.cpython-36m-x86_64-linux-gnu.so
spacy/gold.pyx
spacy/lexeme.cpython-36m-x86_64-linux-gnu.so
spacy/matcher.pyx
spacy/vectors.cpython-36m-x86_64-linux-gnu.so
spacy/tokenizer.pxd
spacy/morphology.pxd
spacy/compat.py
spacy/symbols.pyx
spacy/pipeline.cpython-36m-x86_64-linux-gnu.so
spacy/language.py
spacy/strings.pyx
spacy/__main__.py
spacy/gold.cpython-36m-x86_64-linux-gnu.so
spacy/pipeline.pxd
spacy/lemmatizer.py
spacy/scorer.py
spacy/parts_of_speech.pxd
spacy/strings.pxd
spacy/__init__.py
spacy/attrs.pxd
spacy/attrs.cpython-36m-x86_64-linux-gnu.so
spacy/parts_of_speech.cpython-36m-x86_64-linux-gnu.so
spacy/structs.pxd
spacy/morphology.pyx
spacy/lexeme.pxd
spacy/pipeline.pyx
spacy/typedefs.pyx
spacy/tokenizer.cpython-36m-x86_64-linux-gnu.so
spacy/about.py
spacy/symbols.pxd
spacy/parts_of_speech.pyx
spacy/__init__.pxd
spacy/tokenizer.pyx
spacy/vocab.pyx
spacy/gold.pxd
spacy/morphology.cpython-36m-x86_64-linux-gnu.so
spacy/glossary.py
spacy/util.py
spacy/attrs.pyx
spacy/matcher.cpython-36m-x86_64-linux-gnu.so
spacy/vectors.pyx
spacy/strings.cpython-36m-x86_64-linux-gnu.so
spacy/vocab.pxd
spacy/lang/tag_map.py
spacy/lang/entity_rules.py
spacy/lang/__init__.py
spacy/lang/char_classes.py
spacy/lang/norm_exceptions.py
spacy/lang/tokenizer_exceptions.py
spacy/lang/punctuation.py
spacy/lang/lex_attrs.py
spacy/lang/sv/examples.py
spacy/lang/sv/morph_rules.py
spacy/lang/sv/__init__.py
spacy/lang/sv/tokenizer_exceptions.py
spacy/lang/sv/stop_words.py
spacy/lang/sv/lemmatizer/__init__.py
spacy/lang/sv/lemmatizer/lookup.py
spacy/lang/pl/examples.py
spacy/lang/pl/__init__.py
spacy/lang/pl/tokenizer_exceptions.py
spacy/lang/pl/stop_words.py
spacy/lang/he/examples.py
spacy/lang/he/__init__.py
spacy/lang/he/stop_words.py
spacy/lang/ja/examples.py
spacy/lang/ja/__init__.py
spacy/lang/zh/examples.py
spacy_ci_improve-2.0.5.dist-info/RECORD
spacy_ci_improve-2.0.5.dist-info/METADATA
spacy_ci_improve-2.0.5.dist-info/metadata.json
spacy_ci_improve-2.0.5.dist-info/top_level.txt
spacy_ci_improve-2.0.5.dist-info/WHEEL
spacy_ci_improve-2.0.5.dist-info/DESCRIPTION.rst
