Metadata-Version: 2.0
Name: spacy-ci-improve
Version: 2.0.5
Summary: Industrial-strength Natural Language Processing (NLP) with Python and Cython
Home-page: https://spacy.io
Author: Explosion AI
Author-email: contact@explosion.ai
License: MIT
Platform: UNKNOWN
Classifier: Development Status :: 5 - Production/Stable
Classifier: Environment :: Console
Classifier: Intended Audience :: Developers
Classifier: Intended Audience :: Science/Research
Classifier: License :: OSI Approved :: MIT License
Classifier: Operating System :: POSIX :: Linux
Classifier: Operating System :: MacOS :: MacOS X
Classifier: Operating System :: Microsoft :: Windows
Classifier: Programming Language :: Cython
Classifier: Programming Language :: Python :: 2
Classifier: Programming Language :: Python :: 2.7
Classifier: Programming Language :: Python :: 3
Classifier: Programming Language :: Python :: 3.4
Classifier: Programming Language :: Python :: 3.5
Classifier: Programming Language :: Python :: 3.6
Classifier: Topic :: Scientific/Engineering
Requires-Dist: numpy (>=1.7)
Requires-Dist: murmurhash (<0.29,>=0.28)
Requires-Dist: cymem (<1.32,>=1.30)
Requires-Dist: preshed (<2.0.0,>=1.0.0)
Requires-Dist: thinc (<6.11.0,>=6.10.1)
Requires-Dist: plac (<1.0.0,>=0.9.6)
Requires-Dist: six
Requires-Dist: pathlib
Requires-Dist: ujson (>=1.35)
Requires-Dist: dill (<0.3,>=0.2)
Requires-Dist: requests (<3.0.0,>=2.13.0)
Requires-Dist: regex (==2017.4.5)
Requires-Dist: ftfy (<5.0.0,>=4.4.2)
Requires-Dist: msgpack-python
Requires-Dist: msgpack-numpy (==0.4.1)
